{
  "timestamp": "2026-05-14T04:12:29.539894+00:00",
  "stationCount": 21,
  "totalStations": 253,
  "batchUpdated": 16,
  "errors": 0,
  "dailyRequestsUsed": 31,
  "schedule": "batch=16 at 09:42 IST",
  "stations": {
    "301738571": {
      "name": "HP",
      "lat": 13.0391669,
      "lng": 80.2573351,
      "priority": "high",
      "updatedAt": "2026-05-13T23:15:15.152164+00:00",
      "currentSpeed": 25,
      "freeFlowSpeed": 25,
      "congestion": "low",
      "confidence": 1
    },
    "301738572": {
      "name": "HP",
      "lat": 13.0402403,
      "lng": 80.2468562,
      "priority": "high",
      "updatedAt": "2026-05-13T23:15:15.152164+00:00",
      "currentSpeed": 35,
      "freeFlowSpeed": 35,
      "congestion": "low",
      "confidence": 1
    },
    "301947513": {
      "name": "Fuel Station",
      "lat": 13.0493343,
      "lng": 80.25305,
      "priority": "low",
      "updatedAt": "2026-05-13T23:15:15.152164+00:00",
      "currentSpeed": 32,
      "freeFlowSpeed": 32,
      "congestion": "low",
      "confidence": 1
    },
    "303284326": {
      "name": "Fuel Station",
      "lat": 13.0851617,
      "lng": 80.2835544,
      "priority": "low",
      "updatedAt": "2026-05-13T23:15:15.152164+00:00",
      "currentSpeed": 35,
      "freeFlowSpeed": 35,
      "congestion": "low",
      "confidence": 1
    },
    "303284327": {
      "name": "Fuel Station",
      "lat": 13.0862218,
      "lng": 80.2812471,
      "priority": "low",
      "updatedAt": "2026-05-13T23:15:15.152164+00:00",
      "currentSpeed": 24,
      "freeFlowSpeed": 24,
      "congestion": "low",
      "confidence": 1
    },
    "305933220": {
      "name": "HP",
      "lat": 12.9796614,
      "lng": 80.218483,
      "priority": "high",
      "updatedAt": "2026-05-14T04:12:29.539894+00:00",
      "currentSpeed": 22,
      "freeFlowSpeed": 31,
      "congestion": "medium",
      "confidence": 1
    },
    "308467144": {
      "name": "HP",
      "lat": 13.0311284,
      "lng": 80.2394414,
      "priority": "high",
      "updatedAt": "2026-05-14T04:12:29.539894+00:00",
      "currentSpeed": 25,
      "freeFlowSpeed": 36,
      "congestion": "medium",
      "confidence": 1.0
    },
    "308467145": {
      "name": "Fuel Station",
      "lat": 13.0337218,
      "lng": 80.2382988,
      "priority": "low",
      "updatedAt": "2026-05-14T04:12:29.539894+00:00",
      "currentSpeed": 15,
      "freeFlowSpeed": 19,
      "congestion": "medium",
      "confidence": 0.73
    },
    "308467150": {
      "name": "Fuel Station",
      "lat": 13.0459529,
      "lng": 80.2562406,
      "priority": "low",
      "updatedAt": "2026-05-14T04:12:29.539894+00:00",
      "currentSpeed": 24,
      "freeFlowSpeed": 31,
      "congestion": "medium",
      "confidence": 1
    },
    "308489028": {
      "name": "Hindustan Petroleum",
      "lat": 13.0260196,
      "lng": 80.2661174,
      "priority": "high",
      "updatedAt": "2026-05-14T04:12:29.539894+00:00",
      "currentSpeed": 19,
      "freeFlowSpeed": 19,
      "congestion": "low",
      "confidence": 0.94
    },
    "310830860": {
      "name": "Shanthi Petrol Station",
      "lat": 12.9935494,
      "lng": 80.1850866,
      "priority": "high",
      "updatedAt": "2026-05-14T04:12:29.539894+00:00",
      "currentSpeed": 32,
      "freeFlowSpeed": 38,
      "congestion": "low",
      "confidence": 1
    },
    "313135840": {
      "name": "HP",
      "lat": 13.0534169,
      "lng": 80.252032,
      "priority": "high",
      "updatedAt": "2026-05-14T04:12:29.539894+00:00",
      "currentSpeed": 26,
      "freeFlowSpeed": 32,
      "congestion": "low",
      "confidence": 1
    },
    "313135912": {
      "name": "Fuel Station",
      "lat": 13.0540764,
      "lng": 80.2530457,
      "priority": "low",
      "updatedAt": "2026-05-14T04:12:29.539894+00:00",
      "currentSpeed": 25,
      "freeFlowSpeed": 36,
      "congestion": "medium",
      "confidence": 1.0
    },
    "314688253": {
      "name": "HP",
      "lat": 13.0427775,
      "lng": 80.2677547,
      "priority": "high",
      "updatedAt": "2026-05-14T04:12:29.539894+00:00",
      "currentSpeed": 24,
      "freeFlowSpeed": 31,
      "congestion": "medium",
      "confidence": 1
    },
    "317821274": {
      "name": "HP",
      "lat": 13.0184727,
      "lng": 80.2614032,
      "priority": "high",
      "updatedAt": "2026-05-14T04:12:29.539894+00:00",
      "currentSpeed": 28,
      "freeFlowSpeed": 33,
      "congestion": "low",
      "confidence": 1.0
    },
    "319038955": {
      "name": "Indian Oil",
      "lat": 13.0421221,
      "lng": 80.2684202,
      "priority": "high",
      "updatedAt": "2026-05-14T04:12:29.539894+00:00",
      "currentSpeed": 23,
      "freeFlowSpeed": 23,
      "congestion": "low",
      "confidence": 1
    },
    "325787817": {
      "name": "Indian Oil",
      "lat": 12.9097046,
      "lng": 80.2503011,
      "priority": "high",
      "updatedAt": "2026-05-14T04:12:29.539894+00:00",
      "currentSpeed": 35,
      "freeFlowSpeed": 40,
      "congestion": "low",
      "confidence": 1
    },
    "344405871": {
      "name": "Fuel Station",
      "lat": 13.0674553,
      "lng": 80.2524458,
      "priority": "low",
      "updatedAt": "2026-05-14T04:12:29.539894+00:00",
      "currentSpeed": 22,
      "freeFlowSpeed": 30,
      "congestion": "medium",
      "confidence": 1
    },
    "364572949": {
      "name": "Shell",
      "lat": 13.0247047,
      "lng": 80.2065279,
      "priority": "high",
      "updatedAt": "2026-05-14T04:12:29.539894+00:00",
      "currentSpeed": 27,
      "freeFlowSpeed": 37,
      "congestion": "medium",
      "confidence": 1
    },
    "364651023": {
      "name": "HP",
      "lat": 13.0200917,
      "lng": 80.1853891,
      "priority": "high",
      "updatedAt": "2026-05-14T04:12:29.539894+00:00",
      "currentSpeed": 27,
      "freeFlowSpeed": 31,
      "congestion": "low",
      "confidence": 1.0
    },
    "365544723": {
      "name": "BP",
      "lat": 13.0116259,
      "lng": 80.2185178,
      "priority": "high",
      "updatedAt": "2026-05-14T04:12:29.539894+00:00",
      "currentSpeed": 25,
      "freeFlowSpeed": 36,
      "congestion": "medium",
      "confidence": 1.0
    }
  }
}