{
  "timestamp": "2026-05-30T08:04:47.354644+00:00",
  "stationCount": 22,
  "totalStations": 253,
  "batchUpdated": 10,
  "errors": 0,
  "dailyRequestsUsed": 43,
  "schedule": "batch=10 at 13:34 IST",
  "stations": {
    "1330398917": {
      "name": "Bharat Petroleum",
      "lat": 13.1324427,
      "lng": 80.167533,
      "priority": "high",
      "updatedAt": "2026-05-30T05:35:53.717844+00:00",
      "currentSpeed": 32,
      "freeFlowSpeed": 32,
      "congestion": "low",
      "confidence": 1
    },
    "1354435857": {
      "name": "Shell Petrol Station",
      "lat": 12.9470276,
      "lng": 80.2089755,
      "priority": "high",
      "updatedAt": "2026-05-30T05:35:53.717844+00:00",
      "currentSpeed": 30,
      "freeFlowSpeed": 30,
      "congestion": "low",
      "confidence": 1
    },
    "1395183934": {
      "name": "Fuel Station",
      "lat": 12.9976086,
      "lng": 80.0870973,
      "priority": "low",
      "updatedAt": "2026-05-30T05:35:53.717844+00:00",
      "currentSpeed": 37,
      "freeFlowSpeed": 37,
      "congestion": "low",
      "confidence": 1
    },
    "1501132753": {
      "name": "Chinthamani Cooperative Petrol Bunk",
      "lat": 13.0410061,
      "lng": 80.2373742,
      "priority": "medium",
      "updatedAt": "2026-05-30T05:35:53.717844+00:00",
      "currentSpeed": 20,
      "freeFlowSpeed": 25,
      "congestion": "low",
      "confidence": 0.98
    },
    "248343706": {
      "name": "HP",
      "lat": 13.0368733,
      "lng": 80.2555597,
      "priority": "high",
      "updatedAt": "2026-05-30T05:35:53.717844+00:00",
      "currentSpeed": 17,
      "freeFlowSpeed": 25,
      "congestion": "medium",
      "confidence": 0.98
    },
    "248343893": {
      "name": "IOC",
      "lat": 13.037841,
      "lng": 80.2562967,
      "priority": "high",
      "updatedAt": "2026-05-30T05:35:53.717844+00:00",
      "currentSpeed": 17,
      "freeFlowSpeed": 25,
      "congestion": "medium",
      "confidence": 0.98
    },
    "248344281": {
      "name": "BP",
      "lat": 13.0378885,
      "lng": 80.2569506,
      "priority": "high",
      "updatedAt": "2026-05-30T05:35:53.717844+00:00",
      "currentSpeed": 22,
      "freeFlowSpeed": 27,
      "congestion": "low",
      "confidence": 1.0
    },
    "257532624": {
      "name": "Bharat Petroleum",
      "lat": 12.9943244,
      "lng": 80.1870765,
      "priority": "high",
      "updatedAt": "2026-05-30T05:35:53.717844+00:00",
      "currentSpeed": 38,
      "freeFlowSpeed": 38,
      "congestion": "low",
      "confidence": 1
    },
    "301738571": {
      "name": "HP",
      "lat": 13.0391669,
      "lng": 80.2573351,
      "priority": "high",
      "updatedAt": "2026-05-30T05:35:53.717844+00:00",
      "currentSpeed": 17,
      "freeFlowSpeed": 25,
      "congestion": "medium",
      "confidence": 0.98
    },
    "301738572": {
      "name": "HP",
      "lat": 13.0402403,
      "lng": 80.2468562,
      "priority": "high",
      "updatedAt": "2026-05-30T05:35:53.717844+00:00",
      "currentSpeed": 25,
      "freeFlowSpeed": 35,
      "congestion": "medium",
      "confidence": 1.0
    },
    "301947513": {
      "name": "Fuel Station",
      "lat": 13.0493343,
      "lng": 80.25305,
      "priority": "low",
      "updatedAt": "2026-05-30T05:35:53.717844+00:00",
      "currentSpeed": 32,
      "freeFlowSpeed": 32,
      "congestion": "low",
      "confidence": 1
    },
    "303284326": {
      "name": "Fuel Station",
      "lat": 13.0851617,
      "lng": 80.2835544,
      "priority": "low",
      "updatedAt": "2026-05-30T05:35:53.717844+00:00",
      "currentSpeed": 25,
      "freeFlowSpeed": 35,
      "congestion": "medium",
      "confidence": 1.0
    },
    "303284327": {
      "name": "Fuel Station",
      "lat": 13.0862218,
      "lng": 80.2812471,
      "priority": "low",
      "updatedAt": "2026-05-30T08:04:47.354644+00:00",
      "currentSpeed": 13,
      "freeFlowSpeed": 24,
      "congestion": "medium",
      "confidence": 1
    },
    "305933220": {
      "name": "HP",
      "lat": 12.9796614,
      "lng": 80.218483,
      "priority": "high",
      "updatedAt": "2026-05-30T08:04:47.354644+00:00",
      "currentSpeed": 23,
      "freeFlowSpeed": 32,
      "congestion": "medium",
      "confidence": 1
    },
    "308467144": {
      "name": "HP",
      "lat": 13.0311284,
      "lng": 80.2394414,
      "priority": "high",
      "updatedAt": "2026-05-30T08:04:47.354644+00:00",
      "currentSpeed": 26,
      "freeFlowSpeed": 36,
      "congestion": "medium",
      "confidence": 1.0
    },
    "308467145": {
      "name": "Fuel Station",
      "lat": 13.0337218,
      "lng": 80.2382988,
      "priority": "low",
      "updatedAt": "2026-05-30T08:04:47.354644+00:00",
      "currentSpeed": 12,
      "freeFlowSpeed": 19,
      "congestion": "medium",
      "confidence": 0.63
    },
    "308467150": {
      "name": "Fuel Station",
      "lat": 13.0459529,
      "lng": 80.2562406,
      "priority": "low",
      "updatedAt": "2026-05-30T08:04:47.354644+00:00",
      "currentSpeed": 22,
      "freeFlowSpeed": 31,
      "congestion": "medium",
      "confidence": 1
    },
    "308489028": {
      "name": "Hindustan Petroleum",
      "lat": 13.0260196,
      "lng": 80.2661174,
      "priority": "high",
      "updatedAt": "2026-05-30T08:04:47.354644+00:00",
      "currentSpeed": 22,
      "freeFlowSpeed": 22,
      "congestion": "low",
      "confidence": 1
    },
    "310830860": {
      "name": "Shanthi Petrol Station",
      "lat": 12.9935494,
      "lng": 80.1850866,
      "priority": "high",
      "updatedAt": "2026-05-30T08:04:47.354644+00:00",
      "currentSpeed": 32,
      "freeFlowSpeed": 38,
      "congestion": "low",
      "confidence": 1
    },
    "313135840": {
      "name": "HP",
      "lat": 13.0534169,
      "lng": 80.252032,
      "priority": "high",
      "updatedAt": "2026-05-30T08:04:47.354644+00:00",
      "currentSpeed": 25,
      "freeFlowSpeed": 32,
      "congestion": "medium",
      "confidence": 1
    },
    "313135912": {
      "name": "Fuel Station",
      "lat": 13.0540764,
      "lng": 80.2530457,
      "priority": "low",
      "updatedAt": "2026-05-30T08:04:47.354644+00:00",
      "currentSpeed": 26,
      "freeFlowSpeed": 36,
      "congestion": "medium",
      "confidence": 1.0
    },
    "314688253": {
      "name": "HP",
      "lat": 13.0427775,
      "lng": 80.2677547,
      "priority": "high",
      "updatedAt": "2026-05-30T08:04:47.354644+00:00",
      "currentSpeed": 22,
      "freeFlowSpeed": 31,
      "congestion": "medium",
      "confidence": 1
    }
  }
}